tensonent/__init__.py
tensonent/tensor_algebra/__init__.py
tensonent/tensor_algebra/kronecker.py
tensonent/tensor_algebra/tests/__init__.py
tensonent/tensor_algebra/tests/test_kronecker.py
tensonent-0.1.3.dist-info/LICENSE
tensonent-0.1.3.dist-info/METADATA
tensonent-0.1.3.dist-info/WHEEL
tensonent-0.1.3.dist-info/top_level.txt
tensonent-0.1.3.dist-info/RECORD
