Metadata-Version: 2.1
Name: tensonent
Version: 0.1.3
Summary: Tensor Decomposition Library
Home-page: https://github.com/Tensopy/tensopy
Author: Milad Sadeghi.DM
Author-email: EverLookNeverSee@ProtonMail.ch
License: UNKNOWN
Platform: UNKNOWN
Classifier: Programming Language :: Python :: 3
Classifier: Programming Language :: Python :: 3.7
Classifier: License :: OSI Approved :: MIT License
Classifier: Operating System :: OS Independent
Requires-Python: >=3.7
